[
        {
          "title": "Caja de Luz Guerreras K-Pop",
          "subtitle": "Combate los demonios!",
          "images": [ "fotos/lamparas/huntrix1.jpeg", 
                      "fotos/lamparas/huntrix2.jpeg", 
                      "fotos/lamparas/huntrix3.jpeg"]
        },
        {
          "title": "Escudos luminosos",
          "subtitle": "Ilumina tu pasión",
          "images": [ "fotos/lamparas/lampEscudos1.jpeg", 
                      "fotos/lamparas/lampEscudos2.jpeg",
                      "fotos/lamparas/lampEscudos3.jpeg",
                      "fotos/lamparas/lampEscudos4.jpeg",
                      "fotos/lamparas/lampEscudos5.jpeg",
                      "fotos/lamparas/lampEscudos6.jpeg",
                      "fotos/lamparas/lampEscudos7.jpeg",
                      "fotos/lamparas/lampEscudos8.jpeg"]
        },
        {
          "title": "Clicker Tulipanes",
          "subtitle": "Mata tu estres",
          "images": [
            "fotos/otros/tulipanes1.jpeg"
          ]
        },
        {
          "title": "Thermo Canuto",
          "subtitle": "Esconde tus billetes",
          "images": [
            "fotos/otros/thermoCanuto.jpeg",
            "fotos/otros/thermoCanuto2.jpeg"
          ]
        },
        {
          "title": "Escarapela",
          "subtitle": "Tradicional",
          "images": [
            "fotos/otros/escarapelas1.jpeg"
          ]
        },
        {
          "title": "Escarapela Corazon",
          "subtitle": "Bandera argentina",
          "images": [
            "fotos/sorpresas/escarapelas2.jpeg"
          ]
        }
      ]